<annotation verified="yes">
	<folder>Corrected</folder>
	<filename>20100921.231659.02881.jpg</filename>
	<path>/home/pushyamik/linux_v1.4.0/Corrected/20100921.231659.02881.jpg</path>
	<source>
		<database>Unknown</database>
	</source>
	<size>
		<width>2048</width>
		<height>2048</height>
		<depth>3</depth>
	</size>
	<segmented>0</segmented>
	<object>
		<name>starfish</name>
		<pose>Unspecified</pose>
		<truncated>0</truncated>
		<difficult>0</difficult>
		<bndbox>
			<xmin>1434</xmin>
			<ymin>1665</ymin>
			<xmax>1572</xmax>
			<ymax>1809</ymax>
		</bndbox>
	</object>
	<object>
		<name>fish</name>
		<pose>Unspecified</pose>
		<truncated>0</truncated>
		<difficult>0</difficult>
		<bndbox>
			<xmin>261</xmin>
			<ymin>59</ymin>
			<xmax>478</xmax>
			<ymax>159</ymax>
		</bndbox>
	</object>
</annotation>
