<annotation verified="yes">
	<folder>Corrected</folder>
	<filename>20100921.234250.03501.jpg</filename>
	<path>/home/pushyamik/linux_v1.4.0/Corrected/20100921.234250.03501.jpg</path>
	<source>
		<database>Unknown</database>
	</source>
	<size>
		<width>2048</width>
		<height>2048</height>
		<depth>3</depth>
	</size>
	<segmented>0</segmented>
	<object>
		<name>starfish</name>
		<pose>Unspecified</pose>
		<truncated>0</truncated>
		<difficult>0</difficult>
		<bndbox>
			<xmin>852</xmin>
			<ymin>1556</ymin>
			<xmax>1002</xmax>
			<ymax>1697</ymax>
		</bndbox>
	</object>
	<object>
		<name>starfish</name>
		<pose>Unspecified</pose>
		<truncated>0</truncated>
		<difficult>0</difficult>
		<bndbox>
			<xmin>596</xmin>
			<ymin>480</ymin>
			<xmax>702</xmax>
			<ymax>595</ymax>
		</bndbox>
	</object>
	<object>
		<name>starfish</name>
		<pose>Unspecified</pose>
		<truncated>0</truncated>
		<difficult>0</difficult>
		<bndbox>
			<xmin>78</xmin>
			<ymin>527</ymin>
			<xmax>169</xmax>
			<ymax>612</ymax>
		</bndbox>
	</object>
</annotation>
