<annotation>
	<folder>Corrected</folder>
	<filename>20100922.012133.05868.jpg</filename>
	<path>/home/pushyamik/linux_v1.4.0/Corrected/20100922.012133.05868.jpg</path>
	<source>
		<database>Unknown</database>
	</source>
	<size>
		<width>2048</width>
		<height>2048</height>
		<depth>3</depth>
	</size>
	<segmented>0</segmented>
	<object>
		<name>starfish</name>
		<pose>Unspecified</pose>
		<truncated>0</truncated>
		<difficult>0</difficult>
		<bndbox>
			<xmin>1246</xmin>
			<ymin>939</ymin>
			<xmax>1325</xmax>
			<ymax>1009</ymax>
		</bndbox>
	</object>
	<object>
		<name>coral</name>
		<pose>Unspecified</pose>
		<truncated>0</truncated>
		<difficult>0</difficult>
		<bndbox>
			<xmin>1119</xmin>
			<ymin>1403</ymin>
			<xmax>1311</xmax>
			<ymax>1880</ymax>
		</bndbox>
	</object>
	<object>
		<name>coral</name>
		<pose>Unspecified</pose>
		<truncated>0</truncated>
		<difficult>0</difficult>
		<bndbox>
			<xmin>784</xmin>
			<ymin>1327</ymin>
			<xmax>1325</xmax>
			<ymax>1780</ymax>
		</bndbox>
	</object>
	<object>
		<name>coral</name>
		<pose>Unspecified</pose>
		<truncated>0</truncated>
		<difficult>0</difficult>
		<bndbox>
			<xmin>881</xmin>
			<ymin>1571</ymin>
			<xmax>1064</xmax>
			<ymax>1745</ymax>
		</bndbox>
	</object>
	<object>
		<name>coral</name>
		<pose>Unspecified</pose>
		<truncated>0</truncated>
		<difficult>0</difficult>
		<bndbox>
			<xmin>1102</xmin>
			<ymin>1471</ymin>
			<xmax>1290</xmax>
			<ymax>1715</ymax>
		</bndbox>
	</object>
</annotation>
